lamber_report/__init__.py
lamber_report/frontend/404.html
lamber_report/frontend/index.html
lamber_report/frontend/project.html
lamber_report/frontend/test_session.html
lamber_report/frontend/testcase.html
lamber_report/frontend/_next/static/chunks/290-a49487287a3fcb8c.js
lamber_report/frontend/_next/static/chunks/328-0b0e93d0a1ec5acc.js
lamber_report/frontend/_next/static/chunks/357-4aaeb251814627d5.js
lamber_report/frontend/_next/static/chunks/592-6991c140f1941ad0.js
lamber_report/frontend/_next/static/chunks/899-d120db9056f80b46.js
lamber_report/frontend/_next/static/chunks/939-aaa46ae38b99f7b8.js
lamber_report/frontend/_next/static/chunks/framework-a91291bbb300b8fc.js
lamber_report/frontend/_next/static/chunks/main-4e8fb1a18297d772.js
lamber_report/frontend/_next/static/chunks/polyfills-42372ed130431b0a.js
lamber_report/frontend/_next/static/chunks/webpack-fbb920bddf9bf0a6.js
lamber_report/frontend/_next/static/chunks/pages/_app-048cb56e413077d3.js
lamber_report/frontend/_next/static/chunks/pages/_error-066327c2ba9145df.js
lamber_report/frontend/_next/static/chunks/pages/index-e1fe85284e9405ee.js
lamber_report/frontend/_next/static/chunks/pages/project-8b0025885b54e7f7.js
lamber_report/frontend/_next/static/chunks/pages/test_session-24ff5bac3d67de50.js
lamber_report/frontend/_next/static/chunks/pages/testcase-c6ff836621f9f5b3.js
lamber_report/frontend/_next/static/css/6b467c7e84c11654.css
lamber_report/frontend/_next/static/e3XZY08lBmzQlDYOHD2xK/_buildManifest.js
lamber_report/frontend/_next/static/e3XZY08lBmzQlDYOHD2xK/_ssgManifest.js
lamber_report-0.1.1.dist-info/METADATA
lamber_report-0.1.1.dist-info/WHEEL
lamber_report-0.1.1.dist-info/entry_points.txt
lamber_report-0.1.1.dist-info/licenses/LICENSE.txt
lamber_report-0.1.1.dist-info/RECORD
