Metadata-Version: 2.4
Name: lamber-report
Version: 0.1.1
Summary: Test report based on Lamber project.
Author-email: luizyao <luizyao@163.com>
License-File: LICENSE.txt
Requires-Python: >=3.10
